<annotation>
	<folder>kakipi</folder>
	<filename>IMG_9840.jpg</filename>
	<path>C:\Users\sasimo\Desktop\kakipi\IMG_9840.jpg</path>
	<source>
		<database>Unknown</database>
	</source>
	<size>
		<width>4032</width>
		<height>3024</height>
		<depth>3</depth>
	</size>
	<segmented>0</segmented>
	<object>
		<name>peanut</name>
		<pose>Unspecified</pose>
		<truncated>0</truncated>
		<difficult>0</difficult>
		<bndbox>
			<xmin>1122</xmin>
			<ymin>68</ymin>
			<xmax>1542</xmax>
			<ymax>272</ymax>
		</bndbox>
	</object>
	<object>
		<name>peanut</name>
		<pose>Unspecified</pose>
		<truncated>0</truncated>
		<difficult>0</difficult>
		<bndbox>
			<xmin>926</xmin>
			<ymin>692</ymin>
			<xmax>1266</xmax>
			<ymax>944</ymax>
		</bndbox>
	</object>
	<object>
		<name>peanut</name>
		<pose>Unspecified</pose>
		<truncated>0</truncated>
		<difficult>0</difficult>
		<bndbox>
			<xmin>1182</xmin>
			<ymin>1484</ymin>
			<xmax>1538</xmax>
			<ymax>1800</ymax>
		</bndbox>
	</object>
	<object>
		<name>peanut</name>
		<pose>Unspecified</pose>
		<truncated>0</truncated>
		<difficult>0</difficult>
		<bndbox>
			<xmin>2642</xmin>
			<ymin>956</ymin>
			<xmax>2954</xmax>
			<ymax>1236</ymax>
		</bndbox>
	</object>
	<object>
		<name>peanut</name>
		<pose>Unspecified</pose>
		<truncated>0</truncated>
		<difficult>0</difficult>
		<bndbox>
			<xmin>1974</xmin>
			<ymin>1452</ymin>
			<xmax>2206</xmax>
			<ymax>1856</ymax>
		</bndbox>
	</object>
	<object>
		<name>peanut</name>
		<pose>Unspecified</pose>
		<truncated>0</truncated>
		<difficult>0</difficult>
		<bndbox>
			<xmin>2194</xmin>
			<ymin>2160</ymin>
			<xmax>2586</xmax>
			<ymax>2512</ymax>
		</bndbox>
	</object>
	<object>
		<name>peanut</name>
		<pose>Unspecified</pose>
		<truncated>0</truncated>
		<difficult>0</difficult>
		<bndbox>
			<xmin>3414</xmin>
			<ymin>2028</ymin>
			<xmax>3838</xmax>
			<ymax>2256</ymax>
		</bndbox>
	</object>
</annotation>
